bookied_sync/__init__.py
bookied_sync/participant.py
bookied_sync/bettingmarket.py
bookied_sync/exceptions.py
bookied_sync/bettingmarketgroupresolve.py
bookied_sync/eventgroup.py
bookied_sync/eventstatus.py
bookied_sync/rule.py
bookied_sync/bettingmarketgroup.py
bookied_sync/event.py
bookied_sync/lookup.py
bookied_sync/sport.py
bookied_sync-0.0.3.dist-info/entry_points.txt
bookied_sync-0.0.3.dist-info/top_level.txt
bookied_sync-0.0.3.dist-info/METADATA
bookied_sync-0.0.3.dist-info/DESCRIPTION.rst
bookied_sync-0.0.3.dist-info/metadata.json
bookied_sync-0.0.3.dist-info/WHEEL
bookied_sync-0.0.3.dist-info/RECORD
