Metadata-Version: 2.0
Name: bookied-sync
Version: 0.0.3
Summary: Synchronized objects on the blockchain using proposals wherenecessary
Home-page: http://pbsa.info
Author: Fabian Schuh
Author-email: Fabian.Schuh@BlockchainProjectsBV.com
Maintainer: Fabian Schuh
Maintainer-email: Fabian.Schuh@BlockchainProjectsBV.com
License: UNKNOWN
Download-URL: https://github.com/pbsa/bookied/tarball/0.0.3
Keywords: peerplays,bookie
Platform: UNKNOWN
Classifier: License :: OSI Approved :: MIT License
Classifier: Operating System :: OS Independent
Classifier: Programming Language :: Python :: 3
Classifier: Development Status :: 3 - Alpha
Classifier: Intended Audience :: Developers
Requires-Dist: peerplays
Requires-Dist: pyyaml
Requires-Dist: colorlog
Requires-Dist: dateutils
Requires-Dist: bookiesports
